LICENSE
MANIFEST.in
README.rst
pyproject.toml
setup.cfg
setup.py
django_admin_mazer/__init__.py
django_admin_mazer/apps.py
django_admin_mazer.egg-info/PKG-INFO
django_admin_mazer.egg-info/SOURCES.txt
django_admin_mazer.egg-info/dependency_links.txt
django_admin_mazer.egg-info/requires.txt
django_admin_mazer.egg-info/top_level.txt
django_admin_mazer/templates/admin/404.html
django_admin_mazer/templates/admin/500.html
django_admin_mazer/templates/admin/actions.html
django_admin_mazer/templates/admin/app_index.html
django_admin_mazer/templates/admin/app_list.html
django_admin_mazer/templates/admin/base.html
django_admin_mazer/templates/admin/base_site.html
django_admin_mazer/templates/admin/change_form.html
django_admin_mazer/templates/admin/change_form_object_tools.html
django_admin_mazer/templates/admin/change_list.html
django_admin_mazer/templates/admin/change_list_object_tools.html
django_admin_mazer/templates/admin/change_list_results.html
django_admin_mazer/templates/admin/date_hierarchy.html
django_admin_mazer/templates/admin/delete_confirmation.html
django_admin_mazer/templates/admin/delete_selected_confirmation.html
django_admin_mazer/templates/admin/filter.html
django_admin_mazer/templates/admin/index.html
django_admin_mazer/templates/admin/invalid_setup.html
django_admin_mazer/templates/admin/login.html
django_admin_mazer/templates/admin/nav_sidebar.html
django_admin_mazer/templates/admin/object_history.html
django_admin_mazer/templates/admin/pagination.html
django_admin_mazer/templates/admin/popup_response.html
django_admin_mazer/templates/admin/prepopulated_fields_js.html
django_admin_mazer/templates/admin/search_form.html
django_admin_mazer/templates/admin/submit_line.html
django_admin_mazer/templates/admin/auth/user/add_form.html
django_admin_mazer/templates/admin/auth/user/change_password.html
django_admin_mazer/templates/admin/edit_inline/stacked.html
django_admin_mazer/templates/admin/edit_inline/tabular.html
django_admin_mazer/templates/admin/includes/fieldset.html
django_admin_mazer/templates/admin/includes/object_delete_summary.html
django_admin_mazer/templates/admin/widgets/clearable_file_input.html
